c4m/pdk/sky130/__init__.py
c4m/pdk/sky130/_simulation.py
c4m/pdk/sky130/factory.py
c4m/pdk/sky130/io.py
c4m/pdk/sky130/klayout.py
c4m/pdk/sky130/models/C4M.Sky130_all_lib.spice
c4m/pdk/sky130/models/C4M.Sky130_diode_ff_params.spice
c4m/pdk/sky130/models/C4M.Sky130_diode_fs_params.spice
c4m/pdk/sky130/models/C4M.Sky130_diode_lib.spice
c4m/pdk/sky130/models/C4M.Sky130_diode_model.spice
c4m/pdk/sky130/models/C4M.Sky130_diode_sf_params.spice
c4m/pdk/sky130/models/C4M.Sky130_diode_ss_params.spice
c4m/pdk/sky130/models/C4M.Sky130_diode_tt_params.spice
c4m/pdk/sky130/models/C4M.Sky130_io_ff_model.spice
c4m/pdk/sky130/models/C4M.Sky130_io_fs_model.spice
c4m/pdk/sky130/models/C4M.Sky130_io_lib.spice
c4m/pdk/sky130/models/C4M.Sky130_io_sf_model.spice
c4m/pdk/sky130/models/C4M.Sky130_io_ss_model.spice
c4m/pdk/sky130/models/C4M.Sky130_io_tt_model.spice
c4m/pdk/sky130/models/C4M.Sky130_lib.spice
c4m/pdk/sky130/models/C4M.Sky130_logic_ff_model.spice
c4m/pdk/sky130/models/C4M.Sky130_logic_fs_model.spice
c4m/pdk/sky130/models/C4M.Sky130_logic_lib.spice
c4m/pdk/sky130/models/C4M.Sky130_logic_sf_model.spice
c4m/pdk/sky130/models/C4M.Sky130_logic_ss_model.spice
c4m/pdk/sky130/models/C4M.Sky130_logic_tt_model.spice
c4m/pdk/sky130/models/C4M.Sky130_mim_model.spice
c4m/pdk/sky130/models/C4M.Sky130_npn_f_params.spice
c4m/pdk/sky130/models/C4M.Sky130_npn_lib.spice
c4m/pdk/sky130/models/C4M.Sky130_npn_model.spice
c4m/pdk/sky130/models/C4M.Sky130_npn_s_params.spice
c4m/pdk/sky130/models/C4M.Sky130_npn_t_params.spice
c4m/pdk/sky130/models/C4M.Sky130_pnp_f_params.spice
c4m/pdk/sky130/models/C4M.Sky130_pnp_lib.spice
c4m/pdk/sky130/models/C4M.Sky130_pnp_model.spice
c4m/pdk/sky130/models/C4M.Sky130_pnp_s_params.spice
c4m/pdk/sky130/models/C4M.Sky130_pnp_t_params.spice
c4m/pdk/sky130/models/C4M.Sky130_rc_common_params.spice
c4m/pdk/sky130/models/C4M.Sky130_rc_hh_params.spice
c4m/pdk/sky130/models/C4M.Sky130_rc_hl_params.spice
c4m/pdk/sky130/models/C4M.Sky130_rc_lh_params.spice
c4m_pdk_sky130-0.2.7.dist-info/METADATA
c4m_pdk_sky130-0.2.7.dist-info/WHEEL
c4m_pdk_sky130-0.2.7.dist-info/entry_points.txt
c4m_pdk_sky130-0.2.7.dist-info/licenses/LICENSE.md
c4m_pdk_sky130-0.2.7.dist-info/RECORD
